gym_aloha/__init__.py
gym_aloha/assets/bimanual_viperx_end_effector_insertion.xml
gym_aloha/assets/bimanual_viperx_end_effector_transfer_cube.xml
gym_aloha/assets/bimanual_viperx_insertion.xml
gym_aloha/assets/bimanual_viperx_transfer_cube.xml
gym_aloha/assets/scene.xml
gym_aloha/assets/tabletop.stl
gym_aloha/assets/vx300s_10_custom_finger_left.stl
gym_aloha/assets/vx300s_10_custom_finger_right.stl
gym_aloha/assets/vx300s_10_gripper_finger.stl
gym_aloha/assets/vx300s_11_ar_tag.stl
gym_aloha/assets/vx300s_1_base.stl
gym_aloha/assets/vx300s_2_shoulder.stl
gym_aloha/assets/vx300s_3_upper_arm.stl
gym_aloha/assets/vx300s_4_upper_forearm.stl
gym_aloha/assets/vx300s_5_lower_forearm.stl
gym_aloha/assets/vx300s_6_wrist.stl
gym_aloha/assets/vx300s_7_gripper.stl
gym_aloha/assets/vx300s_8_gripper_prop.stl
gym_aloha/assets/vx300s_9_gripper_bar.stl
gym_aloha/assets/vx300s_dependencies.xml
gym_aloha/assets/vx300s_left.xml
gym_aloha/assets/vx300s_right.xml
gym_aloha/constants.py
gym_aloha/env.py
gym_aloha/tasks/sim.py
gym_aloha/tasks/sim_end_effector.py
gym_aloha/utils.py
gym_aloha-0.1.3.dist-info/METADATA
gym_aloha-0.1.3.dist-info/WHEEL
gym_aloha-0.1.3.dist-info/licenses/LICENSE
gym_aloha-0.1.3.dist-info/RECORD
