Metadata-Version: 2.4
Name: gym-aloha
Version: 0.1.3
Summary: A gym environment for ALOHA
License: Apache-2.0
License-File: LICENSE
Keywords: robotics,deep,reinforcement,learning,aloha,environment,gym,gymnasium,dm-control,mujoco
Author: Rémi Cadène
Author-email: re.cadene@gmail.com
Requires-Python: >=3.10,<4.0
Classifier: Development Status :: 3 - Alpha
Classifier: Intended Audience :: Developers
Classifier: License :: OSI Approved :: Apache Software License
Classifier: Programming Language :: Python :: 3
Classifier: Programming Language :: Python :: 3.10
Classifier: Programming Language :: Python :: 3.11
Classifier: Programming Language :: Python :: 3.12
Classifier: Programming Language :: Python :: 3.13
Classifier: Programming Language :: Python :: 3.14
Classifier: Topic :: Software Development :: Build Tools
Provides-Extra: dev
Provides-Extra: test
Requires-Dist: debugpy (>=1.8.1) ; extra == "dev"
Requires-Dist: dm-control (>=1.0.15)
Requires-Dist: gymnasium (>=0.29.1)
Requires-Dist: imageio[ffmpeg] (>=2.34.0)
Requires-Dist: mujoco (>=3.0.0)
Requires-Dist: pre-commit (>=3.7.0) ; extra == "dev"
Requires-Dist: pytest (>=8.1.0) ; extra == "test"
Requires-Dist: pytest-cov (>=5.0.0) ; extra == "test"
